swea/__init__.py
swea/scripts.py
swea-0.0.2.dist-info/LICENSE
swea-0.0.2.dist-info/METADATA
swea-0.0.2.dist-info/WHEEL
swea-0.0.2.dist-info/entry_points.txt
swea-0.0.2.dist-info/top_level.txt
swea-0.0.2.dist-info/RECORD
