Metadata-Version: 2.1
Name: swea
Version: 0.0.2
Summary: SWEA Problem Set Generator
Home-page: https://github.com/hp-hk/swea.git
Author: John Kang
License: UNKNOWN
Platform: UNKNOWN
Classifier: Programming Language :: Python :: 3
Classifier: License :: OSI Approved :: MIT License
Classifier: Operating System :: OS Independent
Requires-Python: >=3.6
